{
    "countries":  [
                      {
                          "iso":  "AR",
                          "geo_admin":  "Argentina",
                          "display_name":  "Argentina",
                          "continental_region":  "South America",
                          "detail_level":  "mid",
                          "primary_biome":  "pampas_andes_patagonia",
                          "visual_profile":  "pampas_atlantic_patagonia",
                          "capital":  "Buenos Aires",
                          "label_lon":  -64.5,
                          "label_lat":  -37.0,
                          "special_territory":  false,
                          "administrable":  false,
                          "status":  "mid-detail visual context"
                      },
                      {
                          "iso":  "UY",
                          "geo_admin":  "Uruguay",
                          "display_name":  "Uruguay",
                          "continental_region":  "South America",
                          "detail_level":  "low",
                          "primary_biome":  "temperate_coast",
                          "visual_profile":  "small_atlantic_port",
                          "capital":  "Montevideo",
                          "label_lon":  -56.0,
                          "label_lat":  -32.7,
                          "special_territory":  false,
                          "administrable":  false,
                          "status":  "low-detail visual context"
                      },
                      {
                          "iso":  "PY",
                          "geo_admin":  "Paraguay",
                          "display_name":  "Paraguay",
                          "continental_region":  "South America",
                          "detail_level":  "low",
                          "primary_biome":  "interior_chaco",
                          "visual_profile":  "interior_border",
                          "capital":  "Asuncion",
                          "label_lon":  -58.3,
                          "label_lat":  -23.3,
                          "special_territory":  false,
                          "administrable":  false,
                          "status":  "low-detail visual context"
                      }
                  ],
    "cities":  [
                   {
                       "id":  "AR-BUENOS-AIRES",
                       "country_iso":  "AR",
                       "name":  "Buenos Aires",
                       "region":  "South America",
                       "lon":  -58.3816,
                       "lat":  -34.6037,
                       "marker_type":  "capital",
                       "strategic_role":  "capital metropoli puerto",
                       "detail_level":  "mid",
                       "visible_from_zoom":  "global",
                       "port":  true,
                       "capital":  true,
                       "administrable":  false,
                       "major":  true,
                       "description":  "Lectura estrategica placeholder: capital metropoli puerto en AR."
                   },
                   {
                       "id":  "AR-CORDOBA",
                       "country_iso":  "AR",
                       "name":  "Cordoba",
                       "region":  "South America",
                       "lon":  -64.1888,
                       "lat":  -31.4201,
                       "marker_type":  "interior",
                       "strategic_role":  "ciudad interior estrategica",
                       "detail_level":  "mid",
                       "visible_from_zoom":  "regional",
                       "port":  false,
                       "capital":  false,
                       "administrable":  false,
                       "major":  false,
                       "description":  "Lectura estrategica placeholder: ciudad interior estrategica en AR."
                   },
                   {
                       "id":  "AR-ROSARIO",
                       "country_iso":  "AR",
                       "name":  "Rosario",
                       "region":  "South America",
                       "lon":  -60.6505,
                       "lat":  -32.9442,
                       "marker_type":  "interior",
                       "strategic_role":  "fluvial logistica",
                       "detail_level":  "mid",
                       "visible_from_zoom":  "regional",
                       "port":  false,
                       "capital":  false,
                       "administrable":  false,
                       "major":  false,
                       "description":  "Lectura estrategica placeholder: fluvial logistica en AR."
                   },
                   {
                       "id":  "AR-MENDOZA",
                       "country_iso":  "AR",
                       "name":  "Mendoza",
                       "region":  "South America",
                       "lon":  -68.8458,
                       "lat":  -32.8895,
                       "marker_type":  "interior",
                       "strategic_role":  "andina",
                       "detail_level":  "mid",
                       "visible_from_zoom":  "regional",
                       "port":  false,
                       "capital":  false,
                       "administrable":  false,
                       "major":  false,
                       "description":  "Lectura estrategica placeholder: andina en AR."
                   },
                   {
                       "id":  "AR-NEUQUEN",
                       "country_iso":  "AR",
                       "name":  "Neuquen",
                       "region":  "South America",
                       "lon":  -68.0591,
                       "lat":  -38.9516,
                       "marker_type":  "interior",
                       "strategic_role":  "energia patagonia norte",
                       "detail_level":  "mid",
                       "visible_from_zoom":  "regional",
                       "port":  false,
                       "capital":  false,
                       "administrable":  false,
                       "major":  false,
                       "description":  "Lectura estrategica placeholder: energia patagonia norte en AR."
                   },
                   {
                       "id":  "AR-USHUAIA",
                       "country_iso":  "AR",
                       "name":  "Ushuaia",
                       "region":  "South America",
                       "lon":  -68.303,
                       "lat":  -54.8019,
                       "marker_type":  "interior",
                       "strategic_role":  "austral",
                       "detail_level":  "mid",
                       "visible_from_zoom":  "regional",
                       "port":  false,
                       "capital":  false,
                       "administrable":  false,
                       "major":  false,
                       "description":  "Lectura estrategica placeholder: austral en AR."
                   },
                   {
                       "id":  "UY-MONTEVIDEO",
                       "country_iso":  "UY",
                       "name":  "Montevideo",
                       "region":  "South America",
                       "lon":  -56.1645,
                       "lat":  -34.9011,
                       "marker_type":  "capital",
                       "strategic_role":  "capital nacional",
                       "detail_level":  "low",
                       "visible_from_zoom":  "continental",
                       "port":  true,
                       "capital":  true,
                       "administrable":  false,
                       "major":  true,
                       "description":  "Lectura estrategica placeholder: capital nacional en UY."
                   },
                   {
                       "id":  "UY-PUNTA-DEL-ESTE",
                       "country_iso":  "UY",
                       "name":  "Punta del Este",
                       "region":  "South America",
                       "lon":  -54.9378,
                       "lat":  -34.9369,
                       "marker_type":  "interior",
                       "strategic_role":  "ciudad interior estrategica",
                       "detail_level":  "low",
                       "visible_from_zoom":  "regional",
                       "port":  false,
                       "capital":  false,
                       "administrable":  false,
                       "major":  false,
                       "description":  "Lectura estrategica placeholder: ciudad interior estrategica en UY."
                   },
                   {
                       "id":  "PY-ASUNCION",
                       "country_iso":  "PY",
                       "name":  "Asuncion",
                       "region":  "South America",
                       "lon":  -57.5759,
                       "lat":  -25.2637,
                       "marker_type":  "capital",
                       "strategic_role":  "capital nacional",
                       "detail_level":  "low",
                       "visible_from_zoom":  "continental",
                       "port":  false,
                       "capital":  true,
                       "administrable":  false,
                       "major":  true,
                       "description":  "Lectura estrategica placeholder: capital nacional en PY."
                   },
                   {
                       "id":  "PY-CIUDAD-DEL-ESTE",
                       "country_iso":  "PY",
                       "name":  "Ciudad del Este",
                       "region":  "South America",
                       "lon":  -54.6111,
                       "lat":  -25.5167,
                       "marker_type":  "border",
                       "strategic_role":  "ciudad fronteriza",
                       "detail_level":  "low",
                       "visible_from_zoom":  "regional",
                       "port":  false,
                       "capital":  false,
                       "administrable":  false,
                       "major":  false,
                       "description":  "Lectura estrategica placeholder: ciudad fronteriza en PY."
                   }
               ]
}
